{
  "api-health": {
    "server_id": "api-health",
    "status": "UP",
    "response_time": 672.95,
    "error_message": null,
    "checked_at": "2025-08-22T14:06:46.560409+00:00"
  },
  "vingle-main": {
    "server_id": "vingle-main",
    "status": "UP",
    "response_time": 871.53,
    "error_message": null,
    "checked_at": "2025-08-22T14:06:47.433086+00:00"
  },
  "api-embedding": {
    "server_id": "api-embedding",
    "status": "UP",
    "response_time": 662.2,
    "error_message": null,
    "checked_at": "2025-08-22T14:06:48.096544+00:00"
  },
  "dev-api-health": {
    "server_id": "dev-api-health",
    "status": "UP",
    "response_time": 676.93,
    "error_message": null,
    "checked_at": "2025-08-22T14:06:48.774686+00:00"
  }
}