{
  "api-health": {
    "server_id": "api-health",
    "status": "UP",
    "response_time": 1263.98,
    "error_message": null,
    "checked_at": "2025-07-30T01:53:45.504023+00:00"
  },
  "vingle-main": {
    "server_id": "vingle-main",
    "status": "UP",
    "response_time": 714.24,
    "error_message": null,
    "checked_at": "2025-07-30T01:53:46.219384+00:00"
  },
  "api-embedding": {
    "server_id": "api-embedding",
    "status": "UP",
    "response_time": 766.26,
    "error_message": null,
    "checked_at": "2025-07-30T01:53:46.986846+00:00"
  },
  "dev-api-health": {
    "server_id": "dev-api-health",
    "status": "UP",
    "response_time": 753.13,
    "error_message": null,
    "checked_at": "2025-07-30T01:53:47.741204+00:00"
  }
}