{
  "api-health": {
    "server_id": "api-health",
    "status": "UP",
    "response_time": 1669.17,
    "error_message": null,
    "checked_at": "2025-06-28T15:19:49.190635+00:00"
  },
  "vingle-main": {
    "server_id": "vingle-main",
    "status": "UP",
    "response_time": 799.12,
    "error_message": null,
    "checked_at": "2025-06-28T15:19:49.990828+00:00"
  },
  "api-embedding": {
    "server_id": "api-embedding",
    "status": "UP",
    "response_time": 892.89,
    "error_message": null,
    "checked_at": "2025-06-28T15:19:50.884959+00:00"
  },
  "dev-api-health": {
    "server_id": "dev-api-health",
    "status": "UP",
    "response_time": 801.01,
    "error_message": null,
    "checked_at": "2025-06-28T15:19:51.687104+00:00"
  }
}