{
  "api-health": {
    "server_id": "api-health",
    "status": "UP",
    "response_time": 867.49,
    "error_message": null,
    "checked_at": "2025-07-19T10:32:25.843956+00:00"
  },
  "vingle-main": {
    "server_id": "vingle-main",
    "status": "UP",
    "response_time": 825.89,
    "error_message": null,
    "checked_at": "2025-07-19T10:32:26.670967+00:00"
  },
  "api-embedding": {
    "server_id": "api-embedding",
    "status": "UP",
    "response_time": 884.07,
    "error_message": null,
    "checked_at": "2025-07-19T10:32:27.555888+00:00"
  },
  "dev-api-health": {
    "server_id": "dev-api-health",
    "status": "UP",
    "response_time": 839.8,
    "error_message": null,
    "checked_at": "2025-07-19T10:32:28.396644+00:00"
  }
}