{
  "api-health": {
    "server_id": "api-health",
    "status": "UP",
    "response_time": 843.31,
    "error_message": null,
    "checked_at": "2025-09-27T14:44:19.665310+00:00"
  },
  "vingle-main": {
    "server_id": "vingle-main",
    "status": "UP",
    "response_time": 839.45,
    "error_message": null,
    "checked_at": "2025-09-27T14:44:20.505860+00:00"
  },
  "api-embedding": {
    "server_id": "api-embedding",
    "status": "UP",
    "response_time": 783.85,
    "error_message": null,
    "checked_at": "2025-09-27T14:44:21.290818+00:00"
  },
  "dev-api-health": {
    "server_id": "dev-api-health",
    "status": "UP",
    "response_time": 1064.83,
    "error_message": null,
    "checked_at": "2025-09-27T14:44:22.356737+00:00"
  }
}