{
  "api-health": {
    "server_id": "api-health",
    "status": "UP",
    "response_time": 618.71,
    "error_message": null,
    "checked_at": "2025-07-10T07:53:49.864648+00:00"
  },
  "vingle-main": {
    "server_id": "vingle-main",
    "status": "UP",
    "response_time": 472.14,
    "error_message": null,
    "checked_at": "2025-07-10T07:53:50.337830+00:00"
  },
  "api-embedding": {
    "server_id": "api-embedding",
    "status": "UP",
    "response_time": 615.29,
    "error_message": null,
    "checked_at": "2025-07-10T07:53:50.954766+00:00"
  },
  "dev-api-health": {
    "server_id": "dev-api-health",
    "status": "UP",
    "response_time": 453.27,
    "error_message": null,
    "checked_at": "2025-07-10T07:53:51.409150+00:00"
  }
}