{
  "api-health": {
    "server_id": "api-health",
    "status": "UP",
    "response_time": 725.47,
    "error_message": null,
    "checked_at": "2025-08-18T22:53:44.713214+00:00"
  },
  "vingle-main": {
    "server_id": "vingle-main",
    "status": "UP",
    "response_time": 705.49,
    "error_message": null,
    "checked_at": "2025-08-18T22:53:45.419755+00:00"
  },
  "api-embedding": {
    "server_id": "api-embedding",
    "status": "UP",
    "response_time": 652.4,
    "error_message": null,
    "checked_at": "2025-08-18T22:53:46.073270+00:00"
  },
  "dev-api-health": {
    "server_id": "dev-api-health",
    "status": "UP",
    "response_time": 776.7,
    "error_message": null,
    "checked_at": "2025-08-18T22:53:46.851052+00:00"
  }
}