{
  "api-health": {
    "server_id": "api-health",
    "status": "UP",
    "response_time": 778.69,
    "error_message": null,
    "checked_at": "2025-09-26T07:46:23.983116+00:00"
  },
  "vingle-main": {
    "server_id": "vingle-main",
    "status": "UP",
    "response_time": 712.37,
    "error_message": null,
    "checked_at": "2025-09-26T07:46:24.696570+00:00"
  },
  "api-embedding": {
    "server_id": "api-embedding",
    "status": "UP",
    "response_time": 717.99,
    "error_message": null,
    "checked_at": "2025-09-26T07:46:25.415759+00:00"
  },
  "dev-api-health": {
    "server_id": "dev-api-health",
    "status": "UP",
    "response_time": 585.73,
    "error_message": null,
    "checked_at": "2025-09-26T07:46:26.002748+00:00"
  }
}