{
  "api-health": {
    "server_id": "api-health",
    "status": "UP",
    "response_time": 881.23,
    "error_message": null,
    "checked_at": "2025-07-12T19:22:45.339222+00:00"
  },
  "vingle-main": {
    "server_id": "vingle-main",
    "status": "UP",
    "response_time": 1627.43,
    "error_message": null,
    "checked_at": "2025-07-12T19:22:46.967747+00:00"
  },
  "api-embedding": {
    "server_id": "api-embedding",
    "status": "UP",
    "response_time": 805.61,
    "error_message": null,
    "checked_at": "2025-07-12T19:22:47.774509+00:00"
  },
  "dev-api-health": {
    "server_id": "dev-api-health",
    "status": "UP",
    "response_time": 866.07,
    "error_message": null,
    "checked_at": "2025-07-12T19:22:48.641684+00:00"
  }
}