{
  "api-health": {
    "server_id": "api-health",
    "status": "UP",
    "response_time": 839.91,
    "error_message": null,
    "checked_at": "2025-10-10T03:52:30.810025+00:00"
  },
  "vingle-main": {
    "server_id": "vingle-main",
    "status": "UP",
    "response_time": 800.56,
    "error_message": null,
    "checked_at": "2025-10-10T03:52:31.611650+00:00"
  },
  "api-embedding": {
    "server_id": "api-embedding",
    "status": "UP",
    "response_time": 805.11,
    "error_message": null,
    "checked_at": "2025-10-10T03:52:32.417933+00:00"
  },
  "dev-api-health": {
    "server_id": "dev-api-health",
    "status": "UP",
    "response_time": 740.7,
    "error_message": null,
    "checked_at": "2025-10-10T03:52:33.159726+00:00"
  }
}