{
  "api-health": {
    "server_id": "api-health",
    "status": "UP",
    "response_time": 721.91,
    "error_message": null,
    "checked_at": "2025-08-15T11:31:04.874431+00:00"
  },
  "vingle-main": {
    "server_id": "vingle-main",
    "status": "UP",
    "response_time": 718.84,
    "error_message": null,
    "checked_at": "2025-08-15T11:31:05.594404+00:00"
  },
  "api-embedding": {
    "server_id": "api-embedding",
    "status": "UP",
    "response_time": 808.75,
    "error_message": null,
    "checked_at": "2025-08-15T11:31:06.404357+00:00"
  },
  "dev-api-health": {
    "server_id": "dev-api-health",
    "status": "UP",
    "response_time": 811.17,
    "error_message": null,
    "checked_at": "2025-08-15T11:31:07.216676+00:00"
  }
}