{
  "api-health": {
    "server_id": "api-health",
    "status": "UP",
    "response_time": 781.53,
    "error_message": null,
    "checked_at": "2025-09-28T00:54:19.004165+00:00"
  },
  "vingle-main": {
    "server_id": "vingle-main",
    "status": "UP",
    "response_time": 828.29,
    "error_message": null,
    "checked_at": "2025-09-28T00:54:19.833571+00:00"
  },
  "api-embedding": {
    "server_id": "api-embedding",
    "status": "UP",
    "response_time": 776.09,
    "error_message": null,
    "checked_at": "2025-09-28T00:54:20.610813+00:00"
  },
  "dev-api-health": {
    "server_id": "dev-api-health",
    "status": "UP",
    "response_time": 825.97,
    "error_message": null,
    "checked_at": "2025-09-28T00:54:21.437912+00:00"
  }
}