{
  "api-health": {
    "server_id": "api-health",
    "status": "UP",
    "response_time": 652.93,
    "error_message": null,
    "checked_at": "2025-10-04T10:20:15.017838+00:00"
  },
  "vingle-main": {
    "server_id": "vingle-main",
    "status": "UP",
    "response_time": 705.8,
    "error_message": null,
    "checked_at": "2025-10-04T10:20:15.724602+00:00"
  },
  "api-embedding": {
    "server_id": "api-embedding",
    "status": "UP",
    "response_time": 789.08,
    "error_message": null,
    "checked_at": "2025-10-04T10:20:16.514713+00:00"
  },
  "dev-api-health": {
    "server_id": "dev-api-health",
    "status": "UP",
    "response_time": 731.03,
    "error_message": null,
    "checked_at": "2025-10-04T10:20:17.246849+00:00"
  }
}