{
  "api-health": {
    "server_id": "api-health",
    "status": "UP",
    "response_time": 692.15,
    "error_message": null,
    "checked_at": "2025-09-25T14:02:44.182098+00:00"
  },
  "vingle-main": {
    "server_id": "vingle-main",
    "status": "UP",
    "response_time": 708.85,
    "error_message": null,
    "checked_at": "2025-09-25T14:02:44.892001+00:00"
  },
  "api-embedding": {
    "server_id": "api-embedding",
    "status": "UP",
    "response_time": 688.1,
    "error_message": null,
    "checked_at": "2025-09-25T14:02:45.581234+00:00"
  },
  "dev-api-health": {
    "server_id": "dev-api-health",
    "status": "UP",
    "response_time": 694.98,
    "error_message": null,
    "checked_at": "2025-09-25T14:02:46.277206+00:00"
  }
}