{
  "api-health": {
    "server_id": "api-health",
    "status": "UP",
    "response_time": 579.93,
    "error_message": null,
    "checked_at": "2025-08-18T19:30:56.771872+00:00"
  },
  "vingle-main": {
    "server_id": "vingle-main",
    "status": "UP",
    "response_time": 566.67,
    "error_message": null,
    "checked_at": "2025-08-18T19:30:57.339694+00:00"
  },
  "api-embedding": {
    "server_id": "api-embedding",
    "status": "UP",
    "response_time": 430.03,
    "error_message": null,
    "checked_at": "2025-08-18T19:30:57.770883+00:00"
  },
  "dev-api-health": {
    "server_id": "dev-api-health",
    "status": "UP",
    "response_time": 582.88,
    "error_message": null,
    "checked_at": "2025-08-18T19:30:58.354959+00:00"
  }
}