{
  "api-health": {
    "server_id": "api-health",
    "status": "UP",
    "response_time": 618.21,
    "error_message": null,
    "checked_at": "2025-08-09T06:05:38.579863+00:00"
  },
  "vingle-main": {
    "server_id": "vingle-main",
    "status": "UP",
    "response_time": 594.94,
    "error_message": null,
    "checked_at": "2025-08-09T06:05:39.175780+00:00"
  },
  "api-embedding": {
    "server_id": "api-embedding",
    "status": "UP",
    "response_time": 585.01,
    "error_message": null,
    "checked_at": "2025-08-09T06:05:39.761828+00:00"
  },
  "dev-api-health": {
    "server_id": "dev-api-health",
    "status": "UP",
    "response_time": 598.47,
    "error_message": null,
    "checked_at": "2025-08-09T06:05:40.361275+00:00"
  }
}