{
  "api-health": {
    "server_id": "api-health",
    "status": "UP",
    "response_time": 673.64,
    "error_message": null,
    "checked_at": "2025-08-18T18:11:49.718969+00:00"
  },
  "vingle-main": {
    "server_id": "vingle-main",
    "status": "UP",
    "response_time": 774.33,
    "error_message": null,
    "checked_at": "2025-08-18T18:11:50.494445+00:00"
  },
  "api-embedding": {
    "server_id": "api-embedding",
    "status": "UP",
    "response_time": 734.9,
    "error_message": null,
    "checked_at": "2025-08-18T18:11:51.230516+00:00"
  },
  "dev-api-health": {
    "server_id": "dev-api-health",
    "status": "UP",
    "response_time": 716.3,
    "error_message": null,
    "checked_at": "2025-08-18T18:11:51.947929+00:00"
  }
}