{
  "api-health": {
    "server_id": "api-health",
    "status": "UP",
    "response_time": 770.0,
    "error_message": null,
    "checked_at": "2025-10-03T15:29:37.624046+00:00"
  },
  "vingle-main": {
    "server_id": "vingle-main",
    "status": "UP",
    "response_time": 625.77,
    "error_message": null,
    "checked_at": "2025-10-03T15:29:38.250948+00:00"
  },
  "api-embedding": {
    "server_id": "api-embedding",
    "status": "UP",
    "response_time": 636.39,
    "error_message": null,
    "checked_at": "2025-10-03T15:29:38.888567+00:00"
  },
  "dev-api-health": {
    "server_id": "dev-api-health",
    "status": "UP",
    "response_time": 496.87,
    "error_message": null,
    "checked_at": "2025-10-03T15:29:39.386695+00:00"
  }
}