{
  "api-health": {
    "server_id": "api-health",
    "status": "UP",
    "response_time": 611.84,
    "error_message": null,
    "checked_at": "2025-08-21T08:51:00.620790+00:00"
  },
  "vingle-main": {
    "server_id": "vingle-main",
    "status": "UP",
    "response_time": 611.43,
    "error_message": null,
    "checked_at": "2025-08-21T08:51:01.233351+00:00"
  },
  "api-embedding": {
    "server_id": "api-embedding",
    "status": "UP",
    "response_time": 612.69,
    "error_message": null,
    "checked_at": "2025-08-21T08:51:01.847211+00:00"
  },
  "dev-api-health": {
    "server_id": "dev-api-health",
    "status": "UP",
    "response_time": 617.01,
    "error_message": null,
    "checked_at": "2025-08-21T08:51:02.465385+00:00"
  }
}