{
  "api-health": {
    "server_id": "api-health",
    "status": "UP",
    "response_time": 818.03,
    "error_message": null,
    "checked_at": "2025-07-16T13:42:53.222119+00:00"
  },
  "vingle-main": {
    "server_id": "vingle-main",
    "status": "UP",
    "response_time": 803.5,
    "error_message": null,
    "checked_at": "2025-07-16T13:42:54.026969+00:00"
  },
  "api-embedding": {
    "server_id": "api-embedding",
    "status": "UP",
    "response_time": 820.01,
    "error_message": null,
    "checked_at": "2025-07-16T13:42:54.848117+00:00"
  },
  "dev-api-health": {
    "server_id": "dev-api-health",
    "status": "UP",
    "response_time": 875.5,
    "error_message": null,
    "checked_at": "2025-07-16T13:42:55.725035+00:00"
  }
}