{
  "api-health": {
    "server_id": "api-health",
    "status": "UP",
    "response_time": 739.65,
    "error_message": null,
    "checked_at": "2025-07-03T10:00:55.975729+00:00"
  },
  "vingle-main": {
    "server_id": "vingle-main",
    "status": "UP",
    "response_time": 765.88,
    "error_message": null,
    "checked_at": "2025-07-03T10:00:56.742692+00:00"
  },
  "api-embedding": {
    "server_id": "api-embedding",
    "status": "UP",
    "response_time": 753.13,
    "error_message": null,
    "checked_at": "2025-07-03T10:00:57.496951+00:00"
  },
  "dev-api-health": {
    "server_id": "dev-api-health",
    "status": "UP",
    "response_time": 705.77,
    "error_message": null,
    "checked_at": "2025-07-03T10:00:58.203845+00:00"
  }
}