{
  "api-health": {
    "server_id": "api-health",
    "status": "UP",
    "response_time": 678.83,
    "error_message": null,
    "checked_at": "2025-10-14T19:12:26.619335+00:00"
  },
  "vingle-main": {
    "server_id": "vingle-main",
    "status": "UP",
    "response_time": 734.47,
    "error_message": null,
    "checked_at": "2025-10-14T19:12:27.354920+00:00"
  },
  "api-embedding": {
    "server_id": "api-embedding",
    "status": "UP",
    "response_time": 750.55,
    "error_message": null,
    "checked_at": "2025-10-14T19:12:28.106670+00:00"
  },
  "dev-api-health": {
    "server_id": "dev-api-health",
    "status": "UP",
    "response_time": 739.42,
    "error_message": null,
    "checked_at": "2025-10-14T19:12:28.847227+00:00"
  }
}