{
  "api-health": {
    "server_id": "api-health",
    "status": "UP",
    "response_time": 613.55,
    "error_message": null,
    "checked_at": "2025-10-07T16:47:03.666259+00:00"
  },
  "vingle-main": {
    "server_id": "vingle-main",
    "status": "UP",
    "response_time": 569.78,
    "error_message": null,
    "checked_at": "2025-10-07T16:47:04.237227+00:00"
  },
  "api-embedding": {
    "server_id": "api-embedding",
    "status": "UP",
    "response_time": 587.74,
    "error_message": null,
    "checked_at": "2025-10-07T16:47:04.826290+00:00"
  },
  "dev-api-health": {
    "server_id": "dev-api-health",
    "status": "UP",
    "response_time": 580.04,
    "error_message": null,
    "checked_at": "2025-10-07T16:47:05.407767+00:00"
  }
}