{
  "api-health": {
    "server_id": "api-health",
    "status": "UP",
    "response_time": 1079.08,
    "error_message": null,
    "checked_at": "2025-07-31T13:38:47.566324+00:00"
  },
  "vingle-main": {
    "server_id": "vingle-main",
    "status": "UP",
    "response_time": 601.65,
    "error_message": null,
    "checked_at": "2025-07-31T13:38:48.169571+00:00"
  },
  "api-embedding": {
    "server_id": "api-embedding",
    "status": "UP",
    "response_time": 579.46,
    "error_message": null,
    "checked_at": "2025-07-31T13:38:48.750365+00:00"
  },
  "dev-api-health": {
    "server_id": "dev-api-health",
    "status": "UP",
    "response_time": 562.25,
    "error_message": null,
    "checked_at": "2025-07-31T13:38:49.313835+00:00"
  }
}