{
  "api-health": {
    "server_id": "api-health",
    "status": "UP",
    "response_time": 621.06,
    "error_message": null,
    "checked_at": "2025-07-31T21:36:53.365790+00:00"
  },
  "vingle-main": {
    "server_id": "vingle-main",
    "status": "UP",
    "response_time": 608.15,
    "error_message": null,
    "checked_at": "2025-07-31T21:36:53.974980+00:00"
  },
  "api-embedding": {
    "server_id": "api-embedding",
    "status": "UP",
    "response_time": 675.78,
    "error_message": null,
    "checked_at": "2025-07-31T21:36:54.651871+00:00"
  },
  "dev-api-health": {
    "server_id": "dev-api-health",
    "status": "UP",
    "response_time": 489.51,
    "error_message": null,
    "checked_at": "2025-07-31T21:36:55.142487+00:00"
  }
}