{
  "api-health": {
    "server_id": "api-health",
    "status": "UP",
    "response_time": 608.6,
    "error_message": null,
    "checked_at": "2025-09-13T17:15:45.568988+00:00"
  },
  "vingle-main": {
    "server_id": "vingle-main",
    "status": "UP",
    "response_time": 592.31,
    "error_message": null,
    "checked_at": "2025-09-13T17:15:46.162369+00:00"
  },
  "api-embedding": {
    "server_id": "api-embedding",
    "status": "UP",
    "response_time": 648.28,
    "error_message": null,
    "checked_at": "2025-09-13T17:15:46.811824+00:00"
  },
  "dev-api-health": {
    "server_id": "dev-api-health",
    "status": "UP",
    "response_time": 587.05,
    "error_message": null,
    "checked_at": "2025-09-13T17:15:47.400051+00:00"
  }
}