{
  "api-health": {
    "server_id": "api-health",
    "status": "UP",
    "response_time": 711.15,
    "error_message": null,
    "checked_at": "2025-10-02T05:27:19.860465+00:00"
  },
  "vingle-main": {
    "server_id": "vingle-main",
    "status": "UP",
    "response_time": 686.31,
    "error_message": null,
    "checked_at": "2025-10-02T05:27:20.547823+00:00"
  },
  "api-embedding": {
    "server_id": "api-embedding",
    "status": "UP",
    "response_time": 1239.89,
    "error_message": null,
    "checked_at": "2025-10-02T05:27:21.788838+00:00"
  },
  "dev-api-health": {
    "server_id": "dev-api-health",
    "status": "UP",
    "response_time": 687.85,
    "error_message": null,
    "checked_at": "2025-10-02T05:27:22.477861+00:00"
  }
}