{
  "api-health": {
    "server_id": "api-health",
    "status": "UP",
    "response_time": 1221.58,
    "error_message": null,
    "checked_at": "2025-10-06T22:23:11.200858+00:00"
  },
  "vingle-main": {
    "server_id": "vingle-main",
    "status": "UP",
    "response_time": 820.53,
    "error_message": null,
    "checked_at": "2025-10-06T22:23:12.022566+00:00"
  },
  "api-embedding": {
    "server_id": "api-embedding",
    "status": "UP",
    "response_time": 1674.81,
    "error_message": null,
    "checked_at": "2025-10-06T22:23:13.698582+00:00"
  },
  "dev-api-health": {
    "server_id": "dev-api-health",
    "status": "UP",
    "response_time": 611.31,
    "error_message": null,
    "checked_at": "2025-10-06T22:23:14.311050+00:00"
  }
}