{
  "api-health": {
    "server_id": "api-health",
    "status": "UP",
    "response_time": 728.57,
    "error_message": null,
    "checked_at": "2025-08-28T23:41:16.177516+00:00"
  },
  "vingle-main": {
    "server_id": "vingle-main",
    "status": "UP",
    "response_time": 660.79,
    "error_message": null,
    "checked_at": "2025-08-28T23:41:16.839393+00:00"
  },
  "api-embedding": {
    "server_id": "api-embedding",
    "status": "UP",
    "response_time": 784.8,
    "error_message": null,
    "checked_at": "2025-08-28T23:41:17.625339+00:00"
  },
  "dev-api-health": {
    "server_id": "dev-api-health",
    "status": "UP",
    "response_time": 543.61,
    "error_message": null,
    "checked_at": "2025-08-28T23:41:18.170122+00:00"
  }
}