{
  "api-health": {
    "server_id": "api-health",
    "status": "UP",
    "response_time": 791.47,
    "error_message": null,
    "checked_at": "2025-09-08T20:52:17.963677+00:00"
  },
  "vingle-main": {
    "server_id": "vingle-main",
    "status": "UP",
    "response_time": 704.75,
    "error_message": null,
    "checked_at": "2025-09-08T20:52:18.669609+00:00"
  },
  "api-embedding": {
    "server_id": "api-embedding",
    "status": "UP",
    "response_time": 906.27,
    "error_message": null,
    "checked_at": "2025-09-08T20:52:19.577034+00:00"
  },
  "dev-api-health": {
    "server_id": "dev-api-health",
    "status": "UP",
    "response_time": 690.46,
    "error_message": null,
    "checked_at": "2025-09-08T20:52:20.268653+00:00"
  }
}