{
  "api-health": {
    "server_id": "api-health",
    "status": "UP",
    "response_time": 677.3,
    "error_message": null,
    "checked_at": "2025-10-06T23:39:53.729956+00:00"
  },
  "vingle-main": {
    "server_id": "vingle-main",
    "status": "UP",
    "response_time": 623.33,
    "error_message": null,
    "checked_at": "2025-10-06T23:39:54.354261+00:00"
  },
  "api-embedding": {
    "server_id": "api-embedding",
    "status": "UP",
    "response_time": 561.08,
    "error_message": null,
    "checked_at": "2025-10-06T23:39:54.916495+00:00"
  },
  "dev-api-health": {
    "server_id": "dev-api-health",
    "status": "UP",
    "response_time": 1213.85,
    "error_message": null,
    "checked_at": "2025-10-06T23:39:56.131402+00:00"
  }
}