{
  "api-health": {
    "server_id": "api-health",
    "status": "UP",
    "response_time": 620.07,
    "error_message": null,
    "checked_at": "2025-07-27T22:44:22.084001+00:00"
  },
  "vingle-main": {
    "server_id": "vingle-main",
    "status": "UP",
    "response_time": 605.11,
    "error_message": null,
    "checked_at": "2025-07-27T22:44:22.690261+00:00"
  },
  "api-embedding": {
    "server_id": "api-embedding",
    "status": "UP",
    "response_time": 679.84,
    "error_message": null,
    "checked_at": "2025-07-27T22:44:23.371197+00:00"
  },
  "dev-api-health": {
    "server_id": "dev-api-health",
    "status": "UP",
    "response_time": 476.06,
    "error_message": null,
    "checked_at": "2025-07-27T22:44:23.848460+00:00"
  }
}