{
  "api-health": {
    "server_id": "api-health",
    "status": "UP",
    "response_time": 1253.29,
    "error_message": null,
    "checked_at": "2025-10-04T01:02:22.346361+00:00"
  },
  "vingle-main": {
    "server_id": "vingle-main",
    "status": "UP",
    "response_time": 650.78,
    "error_message": null,
    "checked_at": "2025-10-04T01:02:22.998203+00:00"
  },
  "api-embedding": {
    "server_id": "api-embedding",
    "status": "UP",
    "response_time": 687.28,
    "error_message": null,
    "checked_at": "2025-10-04T01:02:23.686691+00:00"
  },
  "dev-api-health": {
    "server_id": "dev-api-health",
    "status": "UP",
    "response_time": 700.54,
    "error_message": null,
    "checked_at": "2025-10-04T01:02:24.388376+00:00"
  }
}