{
  "api-health": {
    "server_id": "api-health",
    "status": "UP",
    "response_time": 785.46,
    "error_message": null,
    "checked_at": "2025-09-28T06:55:56.733045+00:00"
  },
  "vingle-main": {
    "server_id": "vingle-main",
    "status": "UP",
    "response_time": 776.71,
    "error_message": null,
    "checked_at": "2025-09-28T06:55:57.510841+00:00"
  },
  "api-embedding": {
    "server_id": "api-embedding",
    "status": "UP",
    "response_time": 813.3,
    "error_message": null,
    "checked_at": "2025-09-28T06:55:58.325142+00:00"
  },
  "dev-api-health": {
    "server_id": "dev-api-health",
    "status": "UP",
    "response_time": 864.65,
    "error_message": null,
    "checked_at": "2025-09-28T06:55:59.190717+00:00"
  }
}