{
  "api-health": {
    "server_id": "api-health",
    "status": "UP",
    "response_time": 772.22,
    "error_message": null,
    "checked_at": "2025-08-06T15:07:20.170861+00:00"
  },
  "vingle-main": {
    "server_id": "vingle-main",
    "status": "UP",
    "response_time": 681.64,
    "error_message": null,
    "checked_at": "2025-08-06T15:07:20.853606+00:00"
  },
  "api-embedding": {
    "server_id": "api-embedding",
    "status": "UP",
    "response_time": 806.29,
    "error_message": null,
    "checked_at": "2025-08-06T15:07:21.660808+00:00"
  },
  "dev-api-health": {
    "server_id": "dev-api-health",
    "status": "UP",
    "response_time": 943.28,
    "error_message": null,
    "checked_at": "2025-08-06T15:07:22.605263+00:00"
  }
}